ur_material/__init__.py
ur_material/large/__init__.py
ur_material/large/functions.py
ur_material/large/image_enhance_large.py
ur_material/modules/__init__.py
ur_material/modules/add_dots.py
ur_material/modules/add_ink_leak.py
ur_material/modules/add_shadow_final.py
ur_material/modules/add_watermark.py
ur_material/modules/bg_extraction.py
ur_material/modules/color_extraction.py
ur_material/modules/contains_gray.py
ur_material/modules/elastic_transform.py
ur_material/modules/general_quality_reduce.py
ur_material/modules/half_paper.py
ur_material/modules/ink_leak_final.py
ur_material/modules/ink_reduce.py
ur_material/modules/make_it_old_final.py
ur_material/modules/overlap_final.py
ur_material/modules/perspective_transform.py
ur_material/modules/random_break_reduce.py
ur_material/modules/rotate.py
ur_material/modules/scanned.py
ur_material/modules/seperate_binary.py
ur_material/modules/seperate_lines.py
ur_material/modules/texture_overlap.py
ur_material/modules/warp_texture_blur_sticker.py
ur_material/small/__init__.py
ur_material/small/functions.py
ur_material/small/image_enhance_small.py
ur_material-0.1.3.dist-info/LICENSE
ur_material-0.1.3.dist-info/METADATA
ur_material-0.1.3.dist-info/WHEEL
ur_material-0.1.3.dist-info/top_level.txt
ur_material-0.1.3.dist-info/RECORD
