Metadata-Version: 2.1
Name: ur_material
Version: 0.1.3
Classifier: Programming Language :: Python :: 3
Classifier: License :: OSI Approved :: MIT License
Classifier: Operating System :: OS Independent
License-File: LICENSE
Requires-Dist: numpy==1.26.4
Requires-Dist: requests>=2.24.0
Requires-Dist: aiofiles==24.1.0
Requires-Dist: aiohappyeyeballs==2.4.4
Requires-Dist: aiohttp==3.10.6
Requires-Dist: aiosignal==1.3.2
Requires-Dist: async-timeout==4.0.3
Requires-Dist: attrs==24.3.0
Requires-Dist: augraphy==8.2.6
Requires-Dist: azure-common==1.1.28
Requires-Dist: azure-core==1.31.0
Requires-Dist: azure-storage-blob==12.3.1
Requires-Dist: biopython==1.84
Requires-Dist: bounded-pool-executor==0.0.3
Requires-Dist: cairocffi==1.7.1
Requires-Dist: CairoSVG==2.7.1
Requires-Dist: certifi==2024.12.14
Requires-Dist: cffi==1.17.1
Requires-Dist: charset-normalizer==3.4.0
Requires-Dist: contourpy==1.3.0
Requires-Dist: cryptography==44.0.0
Requires-Dist: cssselect2==0.7.0
Requires-Dist: cycler==0.12.1
Requires-Dist: defusedxml==0.7.1
Requires-Dist: fonttools==4.55.3
Requires-Dist: frozenlist==1.5.0
Requires-Dist: html5lib==1.1
Requires-Dist: idna==3.10
Requires-Dist: imageio==2.36.1
Requires-Dist: imgaug==0.4.0
Requires-Dist: importlib_resources==6.4.5
Requires-Dist: isodate==0.7.2
Requires-Dist: Jinja2==2.11.1
Requires-Dist: joblib==1.4.2
Requires-Dist: kiwisolver==1.4.7
Requires-Dist: lazy_loader==0.4
Requires-Dist: llvmlite==0.43.0
Requires-Dist: MarkupSafe==3.0.2
Requires-Dist: matplotlib==3.9.2
Requires-Dist: msrest==0.7.1
Requires-Dist: multidict==6.1.0
Requires-Dist: networkx==3.2.1
Requires-Dist: numba==0.60.0
Requires-Dist: numpy==1.26.4
Requires-Dist: oauthlib==3.2.2
Requires-Dist: opencv-python==4.10.0.84
Requires-Dist: packaging==24.2
Requires-Dist: pandas==2.2.2
Requires-Dist: pillow==11.0.0
Requires-Dist: pqdm==0.2.0
Requires-Dist: propcache==0.2.1
Requires-Dist: pycparser==2.22
Requires-Dist: pyparsing==3.2.0
Requires-Dist: pyphen==0.17.0
Requires-Dist: python-dateutil==2.9.0.post0
Requires-Dist: python-dotenv==1.0.1
Requires-Dist: pytz==2024.2
Requires-Dist: requests==2.32.2
Requires-Dist: requests-oauthlib==2.0.0
Requires-Dist: scikit-image==0.24.0
Requires-Dist: scikit-learn==1.6.0
Requires-Dist: scipy==1.13.1
Requires-Dist: shapely==2.0.6
Requires-Dist: six==1.17.0
Requires-Dist: threadpoolctl==3.5.0
Requires-Dist: tifffile==2024.8.30
Requires-Dist: tinycss2==1.4.0
Requires-Dist: tqdm==4.43.0
Requires-Dist: typing_extensions==4.12.2
Requires-Dist: tzdata==2024.2
Requires-Dist: urllib3==2.2.3
Requires-Dist: WeasyPrint==51
Requires-Dist: webencodings==0.5.1
Requires-Dist: yarl==1.18.3
Requires-Dist: zipp==3.21.0
